{
  "exit_summary": {
    "total_exited": 27,
    "total_active": 2557,
    "exit_rate_percent": 1.044891640866873,
    "last_updated": 1751792445
  },
  "operators_with_exits": [
    {
      "operator": "0x9Db70292b56969F30b1714075cdd091B5B58F8Ae",
      "operator_name": "0x9Db702...58F8Ae",
      "exits": 12,
      "still_active": 0,
      "total_ever": 12,
      "exit_rate": 100.0,
      "latest_exit_timestamp": 1748820695,
      "latest_exit_date": "2025-06-01"
    },
    {
      "operator": "0x37F4C77c17b62fBF34fa8f147539aE9E5117bDEa",
      "operator_name": "0x37F4C7...17bDEa",
      "exits": 6,
      "still_active": 11,
      "total_ever": 17,
      "exit_rate": 35.3,
      "latest_exit_timestamp": 1751479511,
      "latest_exit_date": "2025-07-02"
    },
    {
      "operator": "0xC051C8fbbe18a6990f3E3050ec50D33e96a792F1",
      "operator_name": "0xC051C8...a792F1",
      "exits": 4,
      "still_active": 0,
      "total_ever": 4,
      "exit_rate": 100.0,
      "latest_exit_timestamp": 1747677527,
      "latest_exit_date": "2025-05-19"
    },
    {
      "operator": "0x3621C040D188a3132e84e6039457d54665b57612",
      "operator_name": "Blueavm.eth (0x3621C0...b57612)",
      "exits": 4,
      "still_active": 1,
      "total_ever": 5,
      "exit_rate": 80.0,
      "latest_exit_timestamp": 1747994711,
      "latest_exit_date": "2025-05-23"
    },
    {
      "operator": "0x9909F8C62eE4F0341f3Ca7C13BA075F928f5b787",
      "operator_name": "nodeset.uberudder.eth (0x9909F8...f5b787)",
      "exits": 1,
      "still_active": 16,
      "total_ever": 17,
      "exit_rate": 5.9,
      "latest_exit_timestamp": 1748039255,
      "latest_exit_date": "2025-05-23"
    }
  ],
  "recent_exits": [
    {
      "validator_index": 1906395,
      "operator": "0x37F4C77c17b62fBF34fa8f147539aE9E5117bDEa",
      "operator_name": "0x37F4C7...17bDEa",
      "exit_timestamp": 1751479511,
      "exit_date": "2025-07-02 18:05:11",
      "status": "exited_unslashed",
      "slashed": false,
      "balance_gwei": null,
      "exit_epoch": "376707"
    },
    {
      "validator_index": 1922661,
      "operator": "0x37F4C77c17b62fBF34fa8f147539aE9E5117bDEa",
      "operator_name": "0x37F4C7...17bDEa",
      "exit_timestamp": 1751479511,
      "exit_date": "2025-07-02 18:05:11",
      "status": "exited_unslashed",
      "slashed": false,
      "balance_gwei": null,
      "exit_epoch": "376707"
    },
    {
      "validator_index": 1937869,
      "operator": "0x37F4C77c17b62fBF34fa8f147539aE9E5117bDEa",
      "operator_name": "0x37F4C7...17bDEa",
      "exit_timestamp": 1751479511,
      "exit_date": "2025-07-02 18:05:11",
      "status": "exited_unslashed",
      "slashed": false,
      "balance_gwei": null,
      "exit_epoch": "376707"
    },
    {
      "validator_index": 1896857,
      "operator": "0x37F4C77c17b62fBF34fa8f147539aE9E5117bDEa",
      "operator_name": "0x37F4C7...17bDEa",
      "exit_timestamp": 1750535639,
      "exit_date": "2025-06-21 19:53:59",
      "status": "withdrawal_done",
      "slashed": false,
      "balance_gwei": null,
      "exit_epoch": "374249"
    },
    {
      "validator_index": 1905621,
      "operator": "0x37F4C77c17b62fBF34fa8f147539aE9E5117bDEa",
      "operator_name": "0x37F4C7...17bDEa",
      "exit_timestamp": 1750535639,
      "exit_date": "2025-06-21 19:53:59",
      "status": "withdrawal_done",
      "slashed": false,
      "balance_gwei": null,
      "exit_epoch": "374249"
    },
    {
      "validator_index": 1906294,
      "operator": "0x37F4C77c17b62fBF34fa8f147539aE9E5117bDEa",
      "operator_name": "0x37F4C7...17bDEa",
      "exit_timestamp": 1750535639,
      "exit_date": "2025-06-21 19:53:59",
      "status": "withdrawal_done",
      "slashed": false,
      "balance_gwei": null,
      "exit_epoch": "374249"
    }
  ],
  "exit_timeline": [
    {
      "date": "2025-05-08",
      "voluntary_exits": 1,
      "slashed_exits": 0,
      "total_exits": 1
    },
    {
      "date": "2025-05-19",
      "voluntary_exits": 3,
      "slashed_exits": 0,
      "total_exits": 3
    },
    {
      "date": "2025-05-23",
      "voluntary_exits": 5,
      "slashed_exits": 0,
      "total_exits": 5
    },
    {
      "date": "2025-05-31",
      "voluntary_exits": 6,
      "slashed_exits": 0,
      "total_exits": 6
    },
    {
      "date": "2025-06-01",
      "voluntary_exits": 6,
      "slashed_exits": 0,
      "total_exits": 6
    },
    {
      "date": "2025-06-21",
      "voluntary_exits": 3,
      "slashed_exits": 0,
      "total_exits": 3
    },
    {
      "date": "2025-07-02",
      "voluntary_exits": 3,
      "slashed_exits": 0,
      "total_exits": 3
    }
  ]
}